{
    "title":"Nuriben'i Ne Kadar Tanıyorsun?",
    "questions":[
        {
            "id":1,
            "questionText":"Nuri Çağrı'ya ne diye seslenir?",
            "optionA":"Abi",
            "optionB":"Kral",
            "optionC":"Usta",
            "optionD":"Patron",
            "trueOption":"optionC"
        },
        {
            "id":2,
            "questionText":"Nuri hangi şehirde okuyor?",
            "optionA":"İzmir",
            "optionB":"Kocaeli",
            "optionC":"Ankara",
            "optionD":"İstanbul",
            "trueOption":"optionA"
        },
        {
            "id":3,
            "questionText":"Nuri'nin memleketi neresidir?",
            "optionA":"İzmir",
            "optionB":"Kocaeli",
            "optionC":"Ankara",
            "optionD":"İstanbul",
            "trueOption":"optionB"
        },
        {
            "id":4,
            "questionText":"Nuri'nin en sevdiği oyun?",
            "optionA":"Pummel Party",
            "optionB":"Valorant",
            "optionC":"",
            "optionD":"",
            "trueOption":"optionC"
        },
        {
            "id":5,
            "questionText":"Nuri'nin ev arkadaşının ismi?",
            "optionA":"Çağrı",
            "optionB":"Batuhan",
            "optionC":"Hasan",
            "optionD":"Kerem",
            "trueOption":"optionD"
        },
        {
            "id":6,
            "questionText":"Çağrı Nuri'ye Nasıl Seslenir",
            "optionA":"Nurci",
            "optionB":"Nurimo",
            "optionC":"Nuriço",
            "optionD":"Hepsi",
            "trueOption":"optionD"
        },
        {
            "id":7,
            "questionText":"",
            "optionA":"",
            "optionB":"",
            "optionC":"",
            "optionD":"",
            "trueOption":""
        },
        {
            "id":8,
            "questionText":"",
            "optionA":"",
            "optionB":"",
            "optionC":"",
            "optionD":"",
            "trueOption":""
        },
        {
            "id":9,
            "questionText":"Nuri'nin içmeyi en sevdiği meşrubat?",
            "optionA":"Çay",
            "optionB":"Kahve",
            "optionC":"Kola",
            "optionD":"Enerji İçeceği",
            "trueOption":"optionA"
        },
        {
            "id":10,
            "questionText":"",
            "optionA":"",
            "optionB":"",
            "optionC":"",
            "optionD":"",
            "trueOption":""
        }
    ],
    "result":[
        {
            "title":"Nuriben'i hiç tanımıyorsun 🥺",
            "description":"",
            "image":"https://cdn.discordapp.com/attachments/784115309710934019/802232025326682202/IMG_20210122_061035.png"
        },
        {
            "title":"",
            "description":"",
            "image":""
        },
        {
            "title":"",
            "description":"",
            "image":""
        }
    ]
}